TRecord-1.0.4.data/scripts/trecord
trecord/__init__.py
trecord/command.py
trecord/database.py
trecord/error.py
trecord/keywords.py
trecord/mssql.py
trecord/mysql.py
trecord/oracle.py
trecord/version.py
TRecord-1.0.4.dist-info/LICENSE
TRecord-1.0.4.dist-info/METADATA
TRecord-1.0.4.dist-info/WHEEL
TRecord-1.0.4.dist-info/top_level.txt
TRecord-1.0.4.dist-info/RECORD
