Metadata-Version: 2.1
Name: TRecord
Version: 1.0.4
Summary: An Interactive SQL Client
Home-page: https://github.com/lusaisai/TRecord
Author: lusaisai
Author-email: lusaisai@163.com
License: MIT
Platform: UNKNOWN
Classifier: Programming Language :: Python :: 3
Classifier: License :: OSI Approved :: MIT License
Classifier: Operating System :: OS Independent
Requires-Dist: pygments
Requires-Dist: PyMySQL
Requires-Dist: pyodbc
Requires-Dist: cx-Oracle
Requires-Dist: prompt-toolkit
Requires-Dist: tabulate[widechars]
Requires-Dist: tablib
Requires-Dist: click
